[
  {
    "text": "1B. a) Dadas las moléculas H2S y PF3, razone en cuál o cuáles de ellas el átomo central presenta algún par de electrones sin compartir. b) Justifique la geometría que presenta la molécula de PF3 c) Indique la hibridación del átomo central del H2S. d) ¿Por qué la molécula BF3 es apolar?",
    "topic_name": "T2: Enlace Químico",
    "exam_year": 2025,
    "exam_model": "Desconocido",
    "is_competency_based": false,
    "id": "dul5k8nj4",
    "source_file": "Examen_Titular-A_Quimica.pdf"
  }
]